README.md
setup.py
imageserver/__init__.py
imageserver/server.py
imageserver.egg-info/PKG-INFO
imageserver.egg-info/SOURCES.txt
imageserver.egg-info/dependency_links.txt
imageserver.egg-info/entry_points.txt
imageserver.egg-info/not-zip-safe
imageserver.egg-info/requires.txt
imageserver.egg-info/top_level.txt