Metadata-Version: 1.1
Name: imageserver
Version: 0.1.2
Summary: Host thumbnails for images
Home-page: UNKNOWN
Author: Nidhi
Author-email: chandranidhi45@gmail.com
License: MIT
Platform: UNKNOWN
Classifier: Programming Language :: Python :: 3
Classifier: Operating System :: OS Independent
